dcisionai_mcp_server/ANTHROPIC_COMPLIANCE.md
dcisionai_mcp_server/ARCHITECTURE.md
dcisionai_mcp_server/ARCHITECTURE_DECISION.md
dcisionai_mcp_server/ARCHITECTURE_SUMMARY.md
dcisionai_mcp_server/CLIENT_INTEGRATION.md
dcisionai_mcp_server/CUSTOMER_DEPLOYMENT_GUIDE.md
dcisionai_mcp_server/DEPLOYED_MODELS.md
dcisionai_mcp_server/DEPLOYMENT_ARCHITECTURE.md
dcisionai_mcp_server/FINAL_TEST_INSTRUCTIONS.md
dcisionai_mcp_server/IMPLEMENTATION_PLAN.md
dcisionai_mcp_server/IMPORT_FIX_SUMMARY.md
dcisionai_mcp_server/MIGRATION.md
dcisionai_mcp_server/NEXT_STEPS.md
dcisionai_mcp_server/PROGRESS.md
dcisionai_mcp_server/QUICK_START.md
dcisionai_mcp_server/REACT_CLIENT_STRATEGY.md
dcisionai_mcp_server/README.md
dcisionai_mcp_server/README_TESTING.md
dcisionai_mcp_server/RENAME_MIGRATION_PLAN.md
dcisionai_mcp_server/RETIREMENT_ASSESSMENT.md
dcisionai_mcp_server/RETIREMENT_COMPLETE.md
dcisionai_mcp_server/TESTING.md
dcisionai_mcp_server/TEST_RESULTS.md
dcisionai_mcp_server/TEST_RUN_GUIDE.md
dcisionai_mcp_server/VERIFICATION_REPORT.md
dcisionai_mcp_server/WEBSOCKET_PROTOCOL.md
dcisionai_mcp_server/__init__.py
dcisionai_mcp_server/check_imports.py
dcisionai_mcp_server/config.py
dcisionai_mcp_server/fastmcp_server.py
dcisionai_mcp_server/fastmcp_server.py.bak
dcisionai_mcp_server/fastmcp_server.py.bak2
dcisionai_mcp_server/fastmcp_server.py.bak3
dcisionai_mcp_server/fastmcp_server.py.bak4
dcisionai_mcp_server/health_server.py
dcisionai_mcp_server/mcp_stdio_client.py
dcisionai_mcp_server/requirements.txt
dcisionai_mcp_server/run_test.sh
dcisionai_mcp_server/start_mcp_server.py
dcisionai_mcp_server/start_mcp_server.py.bak11
dcisionai_mcp_server/start_mcp_server.py.bak12
dcisionai_mcp_server/start_server.sh
dcisionai_mcp_server/start_with_worker.py
dcisionai_mcp_server/test_railway_startup.py
dcisionai_mcp_server/test_salesforce_nlp_integration.py
dcisionai_mcp_server/test_simple.py
dcisionai_mcp_server/test_websocket.py
dcisionai_mcp_server/verify_claude_sdk.py
dcisionai_mcp_server-3.2.9.dist-info/METADATA
dcisionai_mcp_server-3.2.9.dist-info/WHEEL
dcisionai_mcp_server-3.2.9.dist-info/entry_points.txt
dcisionai_mcp_server-3.2.9.dist-info/RECORD
