Metadata-Version: 2.4
Name: dcisionai-mcp-server
Version: 3.2.9
Summary: DcisionAI MCP Server - AI-Powered Optimization with Intent Classification & Session Persistence
Project-URL: Homepage, https://dcisionai.com
Project-URL: Repository, https://github.com/ameydhavle/dcisionai-mcp-platform
Project-URL: Issues, https://github.com/ameydhavle/dcisionai-mcp-platform/issues
Project-URL: Documentation, https://github.com/ameydhavle/dcisionai-mcp-platform/blob/main/README.md
Author-email: Amey Dhavle <amey@dcisionai.com>
License: MIT
Keywords: ai,claude,cursor,dame,evolutionary-algorithm,highs,job-shop,llm,mathematical-programming,mcp,optimization,portfolio-optimization,retail-layout,trust-score,vrp,vscode,workforce-scheduling
Classifier: Development Status :: 4 - Beta
Classifier: Intended Audience :: Developers
Classifier: Intended Audience :: Financial and Insurance Industry
Classifier: License :: OSI Approved :: MIT License
Classifier: Operating System :: OS Independent
Classifier: Programming Language :: Python :: 3
Classifier: Programming Language :: Python :: 3.10
Classifier: Programming Language :: Python :: 3.11
Classifier: Programming Language :: Python :: 3.12
Classifier: Programming Language :: Python :: 3.13
Classifier: Topic :: Scientific/Engineering :: Artificial Intelligence
Classifier: Topic :: Scientific/Engineering :: Mathematics
Classifier: Topic :: Software Development :: Libraries :: Python Modules
Requires-Python: >=3.10
Requires-Dist: anthropic>=0.40.0
Requires-Dist: dcisionai-workflow>=1.0.0
Requires-Dist: fastmcp>=2.13.0
Requires-Dist: openai>=1.0.0
Requires-Dist: pydantic>=2.0.0
Requires-Dist: python-dotenv>=1.0.0
Provides-Extra: dev
Requires-Dist: black>=23.0.0; extra == 'dev'
Requires-Dist: pytest-asyncio>=0.21.0; extra == 'dev'
Requires-Dist: pytest>=7.0.0; extra == 'dev'
